{
  "routes": [
    { "id": "0", "label": "0", "targetId": "11", "x": 207, "y": 231 },
    { "id": "1", "label": "1", "targetId": "2", "x": 141, "y": 198 },
    { "id": "2", "label": "2", "targetId": "3", "x": 171, "y": 18 },
    { "id": "3", "label": "3", "targetId": "4", "x": 42, "y": 246 },
    { "id": "4", "label": "4", "targetId": "5", "x": 87, "y": 261 },
    { "id": "5", "label": "5", "targetId": "23", "x": 57, "y": 87 },
    { "id": "6", "label": "6", "targetId": "1", "x": 117, "y": 42 },
    { "id": "7", "label": "7", "targetId": "8", "x": 249, "y": 138 },
    { "id": "8", "label": "8", "targetId": "9", "x": 90, "y": 144 },
    { "id": "9", "label": "9", "targetId": "0", "x": 252, "y": 129 },
    { "id": "10", "label": "10", "targetId": "7", "x": 150, "y": 36 },
    { "id": "11", "label": "11", "targetId": "16", "x": 150, "y": 216 },
    { "id": "12", "label": "12", "targetId": "21", "x": 168, "y": 87 },
    { "id": "13", "label": "13", "targetId": "17", "x": 21, "y": 141 },
    { "id": "14", "label": "14", "targetId": "18", "x": 216, "y": 144 },
    { "id": "15", "label": "15", "targetId": "13", "x": 84, "y": 102 },
    { "id": "16", "label": "16", "targetId": "19", "x": 249, "y": 156 },
    { "id": "17", "label": "17", "targetId": "22", "x": 72, "y": 282 },
    { "id": "18", "label": "18", "targetId": "12", "x": 165, "y": 111 },
    { "id": "19", "label": "19", "targetId": "20", "x": 273, "y": 111 },
    { "id": "20", "label": "20", "targetId": "14", "x": 279, "y": 90 },
    { "id": "21", "label": "21", "targetId": "15", "x": 108, "y": 51 },
    { "id": "22", "label": "22", "targetId": "6", "x": 84, "y": 258 },
    { "id": "23", "label": "23", "targetId": "10", "x": 96, "y": 240 }
  ],
  "exec_time": 3600.0921664237976,
  "great_value": 712.282644631392
}
